MANIFEST.in
README.md
gett.py
setup.py
gettup.egg-info/PKG-INFO
gettup.egg-info/SOURCES.txt
gettup.egg-info/dependency_links.txt
gettup.egg-info/entry_points.txt
gettup.egg-info/not-zip-safe
gettup.egg-info/requires.txt
gettup.egg-info/top_level.txt