Metadata-Version: 1.0
Name: gettup
Version: 0.3.0
Summary: A command-line file sharing utility for ge.tt
Home-page: https://github.com/prakhar1989/gett/
Author: Prakhar Srivastav
Author-email: prakhar1989@gmail.com
License: MIT
Keywords: CLI filesharing file sharing upload command-line
Platform: UNKNOWN
